{"text":"\n     The Director of Public Works shall have authority, in the manner provided by ordinance by the Board of Supervisors: \n     (a)     To order the laying of sewer, water, gas and other mains, conduits or connections, whenever, in view of contemplated street improvements or as a sanitary regulation, such construction is recommended by the City Engineer; and \n     (b)     To order that excavations, fences, embankments or grades on private property in a condition deemed by him as endangering the persons or property of those using the abutting streets, shall be put in such condition as to insure the safety of the public. \n(Added by Ord. 439-96, App. 11/8/96)\n\n","heading":{"title":"1","chaptersection":"53","identifier":"1.53","catch_text":"SEWER, WATER AND OTHER CONNECTIONS."}}