{"text":"\n     Any Person seeking to (1) obtain a Franchise; (2) Transfer a Franchise: (3) extend the term of an existing Franchise, (4) renew a Franchise, or (5) modify an existing Franchise to add new Services that are required to be authorized by a Franchise pursuant to this Chapter, shall submit a signed original of its Proposal and eleven (11) copies to the Clerk of the Board and nine (9) copies to the Department The Clerk of the Board shall make a Proposal available for public inspection. The Proposal must conform to all of the requirements of this Chapter. Requests for other types of Franchise modifications may be processed by the Department without a Proposal, and submitted to the Board for approval. However, nothing herein shall prevent the Department from requiring a Proposal in the event the Department determines, based on the nature of the requested modification, that the public interest would best be served by the submission of a Proposal pursuant to this Article. \n(Added by Ord. 58-00, File No. 000198, App. 4/7/2000)\n\n","heading":{"title":"11","chaptersection":"10","identifier":"11.10","catch_text":"FILING OF PROPOSAL."}}