{"text":"\n     For good cause to protect the public health, safety and welfare, the Director of the Department may request the Director of the Department of Public Works to suspend issuance of excavation permits to a Person who is determined, after notice and a hearing, to be in violation of this Chapter or a Franchise. \n(Added by Ord. 58-00, File No. 000198, App. 4/7/2000)\n\n","heading":{"title":"11","chaptersection":"83","identifier":"11.83","catch_text":"SUSPENSION OF ACTION ON PERMIT APPLICATIONS."}}