{"text":"\n     (a)     Persons who meet the requirements for eligibility for CALM shall receive cash payments pursuant to this Article. Recipients are required to comply with all applicable provisions of this Article and the regulations promulgated thereunder. Recipients who fail to comply with applicable provisions of this Article and the regulations promulgated thereunder may have their assistance withheld and/or decreased and/or discontinued as set forth in Department regulations. \n     (b)     No withholding, decrease, or discontinuance of assistance shall occur unless the person to be affected has been advised of the possibility of such action by means of a Notice of Proposed Action and has been afforded the opportunity for a hearing to dispute the proposed action. \n(Added by Ord. 149-98, App. 5/8/98)\n\n","heading":{"title":"20","chaptersection":"107. ","identifier":"20.107. ","catch_text":"CONTINUING ELIGIBILITY."}}