{"text":"\n     Individuals that access the City's shelters and entities that refer individuals to shelter shall only utilize the shelter system in emergency situations and shall preserve shelter beds for individuals that face an immediate and urgent shelter need, thereby preserving the emergency nature of the shelter system. \n(Added by Ord. 198-03, File No. 030737, App. 8/1/2003)\n\n","heading":{"title":"20","chaptersection":"42. ","identifier":"20.42. ","catch_text":"PRESERVATION OF EMERGENCY NATURE OF SHELTER."}}