{"text":"\n     In undertaking this Surplus City Property Program, the City and County of San Francisco is assuming an undertaking only to promote the general welfare. It is not assuming, nor is it imposing on its officers, commissions, and employees, an obligation for breach of which it is liable in money damages to any person who claims that such breach proximately caused injury. \n(Added by Ord. 227-02, File No. 011498, App. 11/26/2002)\n\n","heading":{"title":"23A","chaptersection":"13","identifier":"23A.13","catch_text":"GENERAL WELFARE."}}