{"text":"\n     (a)     Hearings before an assessment hearing officer appointed under Section \n2B.13 of this Chapter shall be conducted pursuant to the provisions of Article 1.7 (commencing with Section 1636) of the California Revenue and Taxation Code. \n     (b)     An assessment hearing officer may conduct hearings on applications where (1) the applicant is the assessee and has filed an application for reduction in accordance with applicable law, and (2) the property under consideration is a single-family dwelling condominium or cooperative, or a multiple-family dwelling of four units or less, and (3) the applicant has requested that the hearing be held before an assessment hearing officer. The Clerk shall inform applicants of their right to elect a hearing before a hearing officer. \n(Added by Ord. 82-94, App. 2/25/94)\n\n","heading":{"title":"2B","chaptersection":"15","identifier":"2B.15","catch_text":"CONDUCT OF HEARINGS."}}