{"text":"\n     All projects that are not statutorily excluded or categorically exempt from CEQA shall be referred to the Environmental Review Officer, prior to the decision as to whether to carry out or approve the project, for an initial study to establish whether a negative declaration or an environmental impact report is required. \n(Added by Ord. 40-01, File No. 001007, App. 3/16/2001)\n\n","heading":{"title":"31","chaptersection":"09. ","identifier":"31.09. ","catch_text":"DETERMINATION OF NEED FOR EVALUATION."}}