{"text":"\n     The interest rate and any other charges for a conventional RAP loan shall be established pursuant to the provisions of Sections \n32.13 and \n32.23, and may include: \n     (a)     The interest charged the City and County on funds borrowed to carry out the provisions of this Chapter;\n     (b)     An amount needed to provide for possible defaults on outstanding loans;\n     (c)     An amount to cover the cost of servicing loan accounts;\n     (d)     An amount to cover the cost of making hardship loans (as provided for in Article VIII); and\n     (e)     An amount to cover the costs of issuing bonds.\n(Added by Ord. 23-74, App. 1/9/74)\n\n","heading":{"title":"32","chaptersection":"67. ","identifier":"32.67. ","catch_text":"INTEREST RATES AND OTHER LOAN CHARGES."}}