{"text":"\n     (a)     The provisions of Section \n35.4 shall not apply whenever a nuisance results from the negligent, improper, or illegal operation of any Industrial Use. \n     (b)     This Chapter is not intended to supercede or limit any other provisions of the Municipal Code with regard to the regulation and control of Industrial Uses, including, but not limited to, Article 11 of the Health and Safety Code. \n     (c)     This Chapter shall not authorize a change in use or uses where such is otherwise controlled or prohibited by the Municipal Code or any state or federal law. \n     (d)     This Chapter shall not authorize the continuation or expansion of a nonconforming use where such is otherwise controlled or prohibited by the Municipal Code. \n(Added by Ord. 223-06, File No. 060265, App. 8/11/2006)\n\n","heading":{"title":"35","chaptersection":"5. ","identifier":"35.5. ","catch_text":"EXEMPTIONS AND NONAPPLICATION."}}