{"text":"\n     The City and County is hereby authorized to charge Participating Parties application, commitment, financing and other fees, in order to recover all administrative and other costs and expenses incurred in the exercise of the powers and duties' conferred by this Article. The Responsible Department shall transmit a letter agreement or contract to a Participating Party which will obligate such party to pay such fees and expenses as the City and County may charge or incur hereunder. \n(Added by Ord. 12-00, File No. 992117, App. 2/11/2000)\n\n","heading":{"title":"43","chaptersection":"2.10","identifier":"43.2.10","catch_text":"FEES."}}